chunkana/__init__.py
chunkana/adaptive_sizing.py
chunkana/api.py
chunkana/chunker.py
chunkana/code_context.py
chunkana/compat.py
chunkana/config.py
chunkana/exceptions.py
chunkana/header_processor.py
chunkana/hierarchy.py
chunkana/invariant_validator.py
chunkana/metadata_recalculator.py
chunkana/parser.py
chunkana/section_splitter.py
chunkana/table_grouping.py
chunkana/types.py
chunkana/validator.py
chunkana/renderers/__init__.py
chunkana/renderers/formatters.py
chunkana/strategies/__init__.py
chunkana/strategies/base.py
chunkana/strategies/code_aware.py
chunkana/strategies/fallback.py
chunkana/strategies/list_aware.py
chunkana/strategies/structural.py
chunkana/streaming/__init__.py
chunkana/streaming/buffer_manager.py
chunkana/streaming/config.py
chunkana/streaming/fence_tracker.py
chunkana/streaming/split_detector.py
chunkana/streaming/streaming_chunker.py
chunkana-0.1.6.dist-info/METADATA
chunkana-0.1.6.dist-info/WHEEL
chunkana-0.1.6.dist-info/licenses/LICENSE
chunkana-0.1.6.dist-info/RECORD
