Metadata-Version: 2.4
Name: chunkana
Version: 0.1.6
Summary: Intelligent Markdown chunking library for RAG systems
Project-URL: Homepage, https://github.com/asukhodko/chunkana
Project-URL: Documentation, https://github.com/asukhodko/chunkana#readme
Project-URL: Repository, https://github.com/asukhodko/chunkana
Project-URL: Issues, https://github.com/asukhodko/chunkana/issues
Author: asukhodko
License-Expression: MIT
License-File: LICENSE
Keywords: chunking,document-processing,markdown,nlp,rag,text-processing
Classifier: Development Status :: 4 - Beta
Classifier: Intended Audience :: Developers
Classifier: License :: OSI Approved :: MIT License
Classifier: Operating System :: OS Independent
Classifier: Programming Language :: Python :: 3
Classifier: Programming Language :: Python :: 3.12
Classifier: Topic :: Scientific/Engineering :: Artificial Intelligence
Classifier: Topic :: Text Processing :: Markup :: Markdown
Classifier: Typing :: Typed
Requires-Python: >=3.12
Provides-Extra: dev
Requires-Dist: build; extra == 'dev'
Requires-Dist: hypothesis>=6.0; extra == 'dev'
Requires-Dist: mypy>=1.0; extra == 'dev'
Requires-Dist: pytest-cov>=4.0; extra == 'dev'
Requires-Dist: pytest>=7.0; extra == 'dev'
Requires-Dist: ruff>=0.1; extra == 'dev'
Requires-Dist: twine; extra == 'dev'
Provides-Extra: docs
Requires-Dist: mkdocs; extra == 'docs'
Requires-Dist: mkdocs-material; extra == 'docs'
